<?xml version="1.0" encoding="UTF-8"?>
<StringBundle version="1.0">
<String id="STRING_GOTO_IMQQROUP">
No olvides visitar los grupos de IMQQ
</String>
<String id="IDS_GetMoreFaces">
Mas emoticones
</String>
<String id="IDS_Translator">
Traductor
</String>
<String id="IDS_Translator_Tags">
Show;translate;Show translate button in chat window#attach;original;Attach original text#send;automatically;Send automatically#
</String>
<String id="IDS_Translator_Lang">
Configuración de idioma
</String>
<String id="IDS_Translator_Attach">
Adjuntar el texto original
</String>
<String id="IDS_Translator_AutoSend">
Enviar automáticamente
</String>
<String id="IDS_Translator_ShowButton">
Mostrar el botón del traductor en la ventana de chat
</String>
<String id="IDS_Translate">
Traducir(&amp;E)
</String>
<String id="IDS_AddLang">
Añada una opción del traductor
</String>
<String id="IDS_QQIInvite">
Invita a tus amigos a participar en QQ Internacional
</String>
<String id="IDS_QQICannotfind">
No se puede encontrar a tus amigos?
</String>
<String id="CF_DRAW_Graffiti">
Dibujar un Grafiti
</String>
<String id="CF_TranslatePoweredBy">
Desarrollado por Google™ y Youdao Translate 
</String>
<String id="CF_HowToUseTranslator">
Como usar el traductor?
</String>
<String id="CF_TranslatorHotkeyTips">
Consejo: utilice el atajo Alt+E para traducir y enviar el mensaje rápidamente!
</String>
<String id="CF_TranslateBtnTip">
Traducir Alt + E
</String>
<String id="CF_TranslateMenuItem_Help">
Como usar el traductor?
</String>
<String id="IDS_TranslatorTips">
Haz clic aquí o presiona Alt+E para traducir tus mensajes.
</String>
<String id="IDS_TranslatorMenuAttach">
Adjuntar el texto original
</String>
<String id="IDS_TranslatorMenuAuto">
Enviar automáticamente
</String>
<String id="IDS_UploadPicLimit">
Puedes subir todas las imagenes de perfil que quieras una vez que tu nivel de QQ sea 4.
</String>
<String id="IDS_BindEmailTips">
Te es dificil recordar tu numero de QQ? Enlázalo a tu cuenta'
</String>
<String id="HelpTipSystem_Tips1Title">
Personaliza tu perfil
</String>
<String id="HelpTipSystem_Tips1">
Has clic en la foto para editar tu perfil, asi tus amigos podran encontrarte!
</String>
<String id="HelpTipSystem_Tips2Title">
Invita a tus amigos
</String>
<String id="HelpTipSystem_Tips2">
Has clic para invitar a tus amigos a QQ Internacional!
</String>
<String id="HelpTipSystem_Tips3Title">
Buscar grupos y amigos
</String>
<String id="HelpTipSystem_Tips3">
Busca amigos o grupos aqui, por email o numero de QQ.
</String>
<String id="HelpTipSystem_Tips4Title">
QQi mini-aplicaciones
</String>
<String id="HelpTipSystem_Tips4">
No olvides visitar lo ultimo en aplicaciones para QQi: Herramientas, juegos, noticias y mas!
</String>
<String id="HelpTipSystem_Tips5Title">
Personaliza tu imagen
</String>
<String id="HelpTipSystem_Tips5">
Personaliza tu QQi con entretenidos temas y colores!
</String>
<String id="HelpTipSystem_Tips6Title">
Compruebe la configuración
</String>
<String id="HelpTipSystem_Tips6">
Has clic aqui para configurar QQi a tu medida.
</String>
<String id="HelpTipSystem_Tips15">
Todos los mensajes y notificaciones de QQ Int estaran aqui. Haz doble clic o Ctrl+Alt+Z para mostrarlas!
</String>
<String id="Tips_CloseTip_Tips">
Ya has leido todos nuestros tips. Quieres volver a leerlos?
</String>
<String id="Tips_CloseTip_Tips1">
Si, Mostrar estos tips nuevamente.
</String>
<String id="Tips_CloseTip_Tips2">
No, No volver a mostrar estos tips.
</String>
<String id="IDS_RestartLater">
Más tarde
</String>
<String id="IDS_RestartNow">
Ahora
</String>
<String id="IDS_NEEDRESTART">
Has cambiado el lenguaje del software. Los cambios ocurriran una vez que reinicies, deseas hacerlo ahora?
</String>
<String id="IDS_Tips">
Tips
</String>
<String id="IDS_QQLevelLocalTips">
Nivel QQ: $LEVEL$
</String>
<String id="IDS_QQLevelActiveDaysTips">
Active days: $NUM$
</String>
<String id="IDS_QQLevelLocalRemainTips">
Dias requeridos para subir de nivel: $NUM$
</String>
<String id="IDS_QQTranslatorSettings">
Configuración del traductor
</String>
<String id="IDS_QQTranslatorOnly7">
Solo puedes agregar 7 lenguajes.
</String>
<String id="IDS_Translate2">
Traducir
</String>
<String id="IDS_ShareTo">
Compartir
</String>
<String id="FriendFinder">
Buscar amigos
</String>
<String id="Navigator">
Directorio web
</String>
<String id="AllFeeds">
Feeds Box
</String>
<String id="ShareTo">
Share
</String>
<String id="QQI_QuickLink">
Web Directory
</String>
<String id="AppBox_StoreTips">
Abrir App Store
</String>
<String id="AppBox_ManageTips">
Administra tus aplicaciones
</String>
<String id="AppBox_Manage">
Configura
</String>
<String id="AppBox_Done">
Terminado
</String>
<String id="MainPanel_Menus">
Main Menu
</String>
<String id="QQI_AppBox">
Abrir App Store
</String>
<String id="QQI_FeedsBox">
QQi Feeds Box
</String>
<String id="CF_MERGEWINDOW">
Merge Chat Windows
</String>
<String id="FeedsBox_All">
All Feeds
</String>
<String id="FeedsBox_Facebook">
Facebook
</String>
<String id="FeedsBox_Weibo">
Sina Weibo
</String>
<String id="FeedsBox_Instagram">
Instagram
</String>
<String id="FeedsBox_ConnectFacebook">
Connect to Facebook
</String>
<String id="FeedsBox_ConnectFacebookText">
You have not connect to Facebook through QQi, Click the Connect Button.
</String>
<String id="FeedsBox_ConnectSinaWeibo">
Connect to Sina Weibo
</String>
<String id="FeedsBox_ConnectSinaWeiboText">
You have not connect to Sina Weibo through QQi, Click the Connect Button.
</String>
<String id="FeedsBox_ConnectInstagram">
Bind to Instagram
</String>
<String id="FeedsBox_ConnectInstagramText">
You have not connect to Instagram through QQi, Click the Connect Button.
</String>
<String id="FeedsBox_FinishConnect">
Finish
</String>
<String id="Finger_Stranger">
Destino
</String>
<String id="Finger_StrangerTip">
Add new friend
</String>
<String id="Old_Finger_Stranger">
Conoce nuevos amigos
</String>
<String id="IDS_IMPORTEMOTION_FAILED">
La importacion de emoticones personalizados ha fallado.
</String>
<String id="SCANVIRUS_QQDOCTOR">
Doctor QQ
</String>
<String id="Finger_MayInterestText">
Personas a quienes puedes interesar
</String>
<String id="CF_FIRFACE_TIP">
Seleccionar una frase
</String>
<String id="CF_DRAWPIC_TIP">
Dibujar una imagen
</String>
<String id="QQI_WeixinApp">
WeChat
</String>
<String id="IntroWeixin">
WeChat es una aplicación móvil para intercambiar mensajes con QQi en iOS, Android, Windows Phone y la plataforma Symbian
</String>
<String id="DownloadWeixin">
Haga clic aquí para descargar la versión internacional de WeChat
</String>
<String id="Weixin_UserOnline">
Tiene $NUM$ amigos en WeChat ahora mismo:
</String>
<String id="Weixin_UserOffline">
Tiene $NUM$ amigos que pueden recibir mensajes en WeChat:
</String>
<String id="Weixin_User">
Estas $NUM$ personas también están en WeChat. Puede añadirlas a WeChat:
</String>
<String id="IDS_WeiYun_Text">Tencent Cloud</String>
<String id="IDS_FeedBack_EntryTips">
Comentarios
</String>
<String id="IDS_SUBMIT">
Enviar
</String>
<String id="IDS_FEEDBACK">
Comentarios
</String>
<String id="IDS_FEEDBACK_CLOSE">
Cerrar
</String>
<String id="IDS_THANKS">
¡Gracias por sus comentarios!
</String>
<String id="IDS_THANKSAGAIN">
Hemos enviado sus comentarios a nuestro equipo de producto. Continuamente trabajamos en la mejora de QQi para cubrir sus necesidades.
</String>
<String id="TencentWeibo">
Tencent Weibo
</String>
<String id="strMiniPortal_TitleBar">
Hoy QQ International
</String>
<String id="Plugin_Tooltip">
App Box
</String>
<String id="AppBox_NotInstall">
La aplicación no está instalada en el ordenador.
¿Desea descargarla e instalarla ahora?
</String>
<String id="ShareToWinTitle">
Compartir con
</String>
<String id="ShareToWinSend">
Enviar
</String>
<String id="ShareToWinFacebook">
Sincronizar con Facebook
</String>
<String id="ShareToWinSina">
Sincronizar con SinaWeibo
</String>
<String id="ShareToWinQQ">
Sincronizar con mensaje personal QQi
</String>
<String id="ViewPhoto">
Visor de imágenes
</String>
<String id="IDS_Finger_QQiUser">
Gente que te gustaría encontrar
</String>
<String id="UserWizard">
User Guide
</String>
<String id="PostWall">
Administra tus aplicaciones
</String>
<String id="QQI_InstagramBox">
InstaViewer
</String>
<String id="InstagramBox_Popular">
Popular
</String>
<String id="InstagramBox_Search">
Search
</String>
<String id="InstagramBox_Clear">
Clear
</String>
<String id="InstagramBox_Feed">
Feeds
</String>
<String id="InstagramBox_MyPhoto">
My Photos
</String>
<String id="InstagramBox_Login">
Login
</String>
<String id="InstagramBox_Logout">
Logout
</String>
<String id="InstagramBox_Finish">
Finish
</String>
<String id="InstagramFeeds_NoResult">
You don't have any photo feed.
</String>
<String id="InstagramMyPhotos_NoResult">
You haven't posted any photos on Instagram.
</String>
<String id="InstagramSearch_NoResult">
We couldn't find anything mathing your search.
Try more general words.
</String>
<String id="InstagramLogin_DesriptiveText">
Please log in your Instagram acount first.
</String>
<String id="InstagramFinish_DesriptiveText">
Please wait until you've logged in Instagram 
before clicking the Finish button.
</String>
<String id="InstagramFirstPage_Timeout">
Network connection problem. 
Try refresh the page.
</String>
<String id="QQLevel_VipIconTip">
Etapa de crecimiento de socio QQ: VIP
</String>
<String id="QQLevel_NotVipIconTip">
Todavía no activa como socio, haga clic para conocer perrogativas de socio
</String>
<String id="QQLevel_LevelTip">
Grado:
</String>
<String id="QQLevel_LevelAccelerateTip">
Promoción acelerada del grado de QQ del socio QQ
</String>
<String id="QQLevel_ActiveDayTip">
Días activos de QQ:
</String>
<String id="QQLevel_RemainDayTip">
Actualizar restantes días activos:
</String>
<String id="Mutual_Friends">
amigos comunes
</String>
<String id="Mutual_Groups">
Grupo común
</String>
<String id="Mutual_MayHave">
podéis tener amigos comunes
</String>
<String id="URLTip_Official">
Este sitio web es la web oficial de Tencent
</String>
<String id="URLTip_Safe">
Este sitio web se ha detectado y no se ha encontrado ningún riesgo
</String>
<String id="URLTip_Unsure">
No se puede determinar la seguridad del sitio web
</String>
<String id="URLTip_Unsafe">
Esta URL es informada como URL maliciosa por gran número de usuarios
</String>
<String id="Similar_Age">
De edad parecida
</String>
<String id="Similar_Hometown">
Viene de la misma población
</String>
<String id="Similar_Chance">
Buena fortuna
</String>
<String id="Similar_Suit">
Con un horóscopo compatible
</String>
<String id="Similar_City">
Viven en la misma ciudad
</String>
<String id="Similar_Horoscope">
Tiene el mismo horóscopo
</String>
<String id="MainMenu_Settings">
Configuración
</String>
<String id="MainMenu_Guide">
Guía del usuario
</String>
<String id="MainMenu_Find">
Buscar amigos
</String>
<String id="MainMenu_Invite">
Invitar a amigos
</String>
<String id="MainMenu_Follow">
Síguenos
</String>
<String id="MainMenu_QQiBlog">
Blog QQi
</String>
<String id="MainMenu_Facebook">
Facebook
</String>
<String id="MainMenu_Twitter">
Twitter
</String>
<String id="MainMenu_Google">
Google+
</String>
<String id="MainMenu_TWeibo">
Tencent Weibo
</String>
<String id="MainMenu_Help">
Centro de ayuda
</String>
<String id="MainMenu_Password">
Recuperación de contraseña
</String>
<String id="MainMenu_Feedback">
Comentarios
</String>
<String id="MainMenu_About">
Acerca de nosotros
</String>
<String id="MainMenu_WhatNew">
Novedades
</String>
<String id="MainMenu_Update">
Actualizar ahora
</String>
<String id="MainMenu_QQiWebsite">
Sitio web QQi
</String>
<String id="MainMenu_Logout">
Cerrar sesión
</String>
<String id="MainMenu_AboutQQi">
Acerca de QQ International
</String>
<String id="Finder_BubbleTips">
Busca amigos aquí.
</String>
<String id="Profile_BubbleTips">
Completa el perfil aquí.
</String>
<String id="Title_CreateGroup">
Crear un grupo
</String>
<String id="AuthMenu_MyWorkPlace">
¿Dónde trabajo?
</String>
<String id="AuthMenu_MyBirthday">
¿Cuándo es mi cumpleaños?
</String>
<String id="AuthMenu_MyPhone">
¿Cuál es mi número de teléfono?
</String>
<String id="AuthMenu_MyName">
¿Cuál es mi nombre real?
</String>
<String id="AuthMenu_MyFavoriteFood">
¿Cuál es mi comida favorita?
</String>
<String id="GroupToolBarTips_CreateDiscussion">
Crear un debate
</String>
<String id="GroupToolBarTips_GroupAlbum">
Álbum de fotos de grupo
</String>
<String id="UserWizard_ProductBlog">
Product Blog
</String>
<String id="UserWizard_FacebookPage">
Facebook Page
</String>
<String id="BtnTip_NoneYouMayKnow">
You can find people to chat with based
on your search criteria. Let's go!
</String>
<String id="UIMgr_WinTitle">
Modificar
</String>
<String id="UIMgr_ThemeTag">
Tema
</String>
<String id="UIMgr_ThemeTagTip">
Da un nuevo aspecto a tu ventana de QQ
</String>
<String id="UIMgr_MainPanelTag">
Panel principal
</String>
<String id="UIMgr_MainPanelTagTip">
Personaliza los accesos directos en el panel principal.
</String>
<String id="UIMgr_QuickList">
Accesos directos al pie
</String>
<String id="UIMgr_PersonalInfo">
Accesos directos al encabezado
</String>
<String id="UIMgr_MoveBtnText">
Mover
</String>
<String id="UIMgr_WeatherCheckText">
Clima
</String>
<String id="ErrorWords_FloatTranslate">
(Traducción imposible: mensaje demasiado largo (max. 200 caracteres) o problemas de connection.)
</String>
<String id="FaceMgr_FacePack">
Todos los archivos(*.eip;*.eif)|*.eip;*.eif| Pack de emoticones (*.eip)|*.eip| Emoticones exportados (*.eif)|*.eif||
</String>
<String id="Error">
Error
</String>
<String id="ContactFolderUnknown">
Grupo sin nombre
</String>
<String id="GenderUnknown">
-
</String>
<String id="UtilInfo_ElmCount">
Total: $COUNT$
</String>
<String id="Group_Group">
Grupos
</String>
<String id="Group_Discuss">
Discusiones
</String>
<String id="Group_Org">
Organización del grupo
</String>
<String id="Group_File_MoveFail">
Fallo al mover la carpeta a $PATH$
</String>
<String id="Group_Connected_Server_Error">
Conexion al servidor de archivos del grupo fallida
</String>
<String id="Group_Connect_Server_Error">
Fallo al conectar al servidor de archivos del grupo
</String>
<String id="Group_RequestSend_Error">
El servidor rechazo la solicitud para enviar una imagen.
</String>
<String id="FACE_TOOL_TIP0">
Smile
</String>
<String id="FACE_TOOL_TIP1">
Grimace
</String>
<String id="FACE_TOOL_TIP2">
Drooling
</String>
<String id="FACE_TOOL_TIP3">
Scowl
</String>
<String id="FACE_TOOL_TIP4">
Chill
</String>
<String id="FACE_TOOL_TIP5">
Sob
</String>
<String id="FACE_TOOL_TIP6">
Shy
</String>
<String id="FACE_TOOL_TIP7">
Silence
</String>
<String id="FACE_TOOL_TIP8">
Sleep
</String>
<String id="FACE_TOOL_TIP9">
Cry
</String>
<String id="FACE_TOOL_TIP10">
Embarrassed
</String>
<String id="FACE_TOOL_TIP11">
En llamas
</String>
<String id="FACE_TOOL_TIP12">
Guiño
</String>
<String id="FACE_TOOL_TIP13">
Grin
</String>
<String id="FACE_TOOL_TIP14">
Surprised
</String>
<String id="FACE_TOOL_TIP15">
Frown
</String>
<String id="FACE_TOOL_TIP16">
Cool
</String>
<String id="FACE_TOOL_TIP17">
Blush
</String>
<String id="FACE_TOOL_TIP18">
Scream
</String>
<String id="FACE_TOOL_TIP19">
Puke
</String>
<String id="FACE_TOOL_TIP20">
Chuckle
</String>
<String id="FACE_TOOL_TIP21">
Pleased
</String>
<String id="FACE_TOOL_TIP22">
Doubtful
</String>
<String id="FACE_TOOL_TIP23">
Smug
</String>
<String id="FACE_TOOL_TIP24">
Sneer
</String>
<String id="FACE_TOOL_TIP25">
Drowsy
</String>
<String id="FACE_TOOL_TIP26">
Panic
</String>
<String id="FACE_TOOL_TIP27">
Sweating
</String>
<String id="FACE_TOOL_TIP28">
Laugh
</String>
<String id="FACE_TOOL_TIP29">
Soldier
</String>
<String id="FACE_TOOL_TIP30">
Strive
</String>
<String id="FACE_TOOL_TIP31">
Scold
</String>
<String id="FACE_TOOL_TIP32">
Confused
</String>
<String id="FACE_TOOL_TIP33">
Shhh
</String>
<String id="FACE_TOOL_TIP34">
Hypnotized
</String>
<String id="FACE_TOOL_TIP35">
Frustrated
</String>
<String id="FACE_TOOL_TIP36">
In the Dark
</String>
<String id="FACE_TOOL_TIP37">
Skull
</String>
<String id="FACE_TOOL_TIP38">
Hammer
</String>
<String id="FACE_TOOL_TIP39">
Wave
</String>
<String id="FACE_TOOL_TIP40">
Relieved
</String>
<String id="FACE_TOOL_TIP41">
Pick Nose
</String>
<String id="FACE_TOOL_TIP42">
Applause
</String>
<String id="FACE_TOOL_TIP43">
Flushed
</String>
<String id="FACE_TOOL_TIP44">
Hellooo
</String>
<String id="FACE_TOOL_TIP45">
Snub 1
</String>
<String id="FACE_TOOL_TIP46">
Snub 2
</String>
<String id="FACE_TOOL_TIP47">
Yawn
</String>
<String id="FACE_TOOL_TIP48">
Booo
</String>
<String id="FACE_TOOL_TIP49">
Distressed
</String>
<String id="FACE_TOOL_TIP50">
Sniffle
</String>
<String id="FACE_TOOL_TIP51">
Sly
</String>
<String id="FACE_TOOL_TIP52">
Pucker
</String>
<String id="FACE_TOOL_TIP53">
Uh Oh
</String>
<String id="FACE_TOOL_TIP54">
Whimper
</String>
<String id="FACE_TOOL_TIP55">
Cleaver
</String>
<String id="FACE_TOOL_TIP56">
Water Melon
</String>
<String id="FACE_TOOL_TIP57">
Beer
</String>
<String id="FACE_TOOL_TIP58">
Basketball
</String>
<String id="FACE_TOOL_TIP59">
Ping Pong
</String>
<String id="FACE_TOOL_TIP60">
Coffee
</String>
<String id="FACE_TOOL_TIP61">
Rice
</String>
<String id="FACE_TOOL_TIP62">
Pig
</String>
<String id="FACE_TOOL_TIP63">
Rose
</String>
<String id="FACE_TOOL_TIP64">
Wilt
</String>
<String id="FACE_TOOL_TIP65">
Kisses
</String>
<String id="FACE_TOOL_TIP66">
Heart
</String>
<String id="FACE_TOOL_TIP67">
Broken Heart
</String>
<String id="FACE_TOOL_TIP68">
Cake
</String>
<String id="FACE_TOOL_TIP69">
Lightning
</String>
<String id="FACE_TOOL_TIP70">
Bomb
</String>
<String id="FACE_TOOL_TIP71">
Dagger
</String>
<String id="FACE_TOOL_TIP72">
Soccer
</String>
<String id="FACE_TOOL_TIP73">
Ladybug
</String>
<String id="FACE_TOOL_TIP74">
Poop
</String>
<String id="FACE_TOOL_TIP75">
Moon
</String>
<String id="FACE_TOOL_TIP76">
Sun
</String>
<String id="FACE_TOOL_TIP77">
Present
</String>
<String id="FACE_TOOL_TIP78">
Hug
</String>
<String id="FACE_TOOL_TIP79">
Thumbs Up
</String>
<String id="FACE_TOOL_TIP80">
Thumbs Down
</String>
<String id="FACE_TOOL_TIP81">
Shake
</String>
<String id="FACE_TOOL_TIP82">
Victory
</String>
<String id="FACE_TOOL_TIP83">
Admire
</String>
<String id="FACE_TOOL_TIP84">
Beckon
</String>
<String id="FACE_TOOL_TIP85">
Fist
</String>
<String id="FACE_TOOL_TIP86">
Pinky
</String>
<String id="FACE_TOOL_TIP87">
Love
</String>
<String id="FACE_TOOL_TIP88">
No No
</String>
<String id="FACE_TOOL_TIP89">
Aceptar
</String>
<String id="FACE_TOOL_TIP90">
Lovebirds
</String>
<String id="FACE_TOOL_TIP91">
In Love
</String>
<String id="FACE_TOOL_TIP92">
Waddle
</String>
<String id="FACE_TOOL_TIP93">
Sit
</String>
<String id="FACE_TOOL_TIP94">
Aaagh!
</String>
<String id="FACE_TOOL_TIP95">
Twirl
</String>
<String id="FACE_TOOL_TIP96">
Bow
</String>
<String id="FACE_TOOL_TIP97">
Turn Away
</String>
<String id="FACE_TOOL_TIP98">
Jump
</String>
<String id="FACE_TOOL_TIP99">
Surrender
</String>
<String id="FACE_TOOL_TIP100">
Hooray
</String>
<String id="FACE_TOOL_TIP101">
Hey Hey
</String>
<String id="FACE_TOOL_TIP102">
Smooches
</String>
<String id="FACE_TOOL_TIP103">
Fighting Girl
</String>
<String id="FACE_TOOL_TIP104">
Fighting Boy
</String>
<String id="FACE_TOOL_TIP105">
Flu
</String>
<String id="FACE_TOOL_TIP106">
Go
</String>
<String id="FACE_TOOL_TIP107">
Seeking
</String>
<String id="FACE_TOOL_TIP108">
Chica bonita
</String>
<String id="FACE_TOOL_TIP109">
Gato
</String>
<String id="FACE_TOOL_TIP110">
Perro
</String>
<String id="FACE_TOOL_TIP111">
Dinero
</String>
<String id="FACE_TOOL_TIP112">
Ampolleta
</String>
<String id="FACE_TOOL_TIP113">
Goblet
</String>
<String id="FACE_TOOL_TIP114">
Musica
</String>
<String id="FACE_TOOL_TIP115">
Pildora
</String>
<String id="FACE_TOOL_TIP116">
Beso
</String>
<String id="FACE_TOOL_TIP117">
Reunion
</String>
<String id="FACE_TOOL_TIP118">
Telefono
</String>
<String id="FACE_TOOL_TIP119">
Reloj
</String>
<String id="FACE_TOOL_TIP120">
Correo
</String>
<String id="FACE_TOOL_TIP121">
TV
</String>
<String id="FACE_TOOL_TIP122">
DuoDuo
</String>
<String id="FACE_TOOL_TIP123">
Beauty
</String>
<String id="FACE_TOOL_TIP124">
Hunlan
</String>
<String id="FACE_TOOL_TIP125">
MoMo
</String>
<String id="FACE_TOOL_TIP126">
Q boy
</String>
<String id="FACE_TOOL_TIP127">
Wine
</String>
<String id="FACE_TOOL_TIP128">
Cola
</String>
<String id="FACE_TOOL_TIP129">
Lluvia
</String>
<String id="FACE_TOOL_TIP130">
Cloudy
</String>
<String id="FACE_TOOL_TIP131">
Snowman
</String>
<String id="FACE_TOOL_TIP132">
Star
</String>
<String id="FACE_TOOL_TIP133">
Female
</String>
<String id="FACE_TOOL_TIP134">
Male
</String>
<String id="TencentWhiteURL_Tips">
Este es el sitio oficial de Tencent. Bienvenido!
</String>
<String id="SYS_MESSAGEBOX_CANCEL">
Cancelar
</String>
<String id="SYS_MESSAGEBOX_RETRY">
Reintentar
</String>
<String id="SYS_MESSAGEBOX_ABORT">
Abortar
</String>
<String id="SYS_MESSAGEBOX_IGNORE">
Ignorar
</String>
<String id="SYS_MESSAGEBOX_CONTINUE">
Continuar
</String>
<String id="SYS_MESSAGEBOX_HELP">
Ayuda
</String>
<String id="CF_Group_Image_TooLarge">
El tamaño de la imagen excede el limite. No pudo ser enviado
</String>
<String id="CF_Group_Image_TooBig">
El tamaño del archivo excede el limite. No pudo ser enviado
</String>
<String id="CF_Group_Image_TooManyCustomFace">
Error: Estas enviando demasiados emoticones.
</String>
<String id="CF_Group_Image_TooManyImage">
Error: Hay muchas imagenes para ser enviadas.
</String>
<String id="CF_OUT_Discuss">
Discusiones Normales
</String>
<String id="CF_PLEASE_ADDMEM_TIPS">
Por favor, seleccione un contacto.
</String>
<String id="SERVICENAME_PAIPAI">
Paipai
</String>
<String id="SERVICENAME_QZONE">
QZone
</String>
<String id="Rich_DEF_FONT">
Tahoma
</String>
<String id="MainPanel_AdjustColor">
Opciones de apariencia
</String>
<String id="TIP_VIEW">
Ver
</String>
<String id="TIP_BUTTON_TIP">
Haga clic para aprender mas
</String>
<String id="ContactInfoTab_BasicInfo">
Informacion basica
</String>
<String id="ContactInfoTab_MoreInfo">
Detalles
</String>
<String id="AddBuddy_Accept">
$CON$ ha aceptado tu solicitud.
</String>
<String id="HotKey_NoSet">
Ninguno
</String>
<String id="HotKey_DoubleCtrl">
双击 Ctrl 键
</String>
<String id="HotKey_DoubleAlt">
双击 Alt 键
</String>
<String id="HotKey_DoubleShift">
双击 Shift 键
</String>
<String id="MSGFILE_IN_SHARE">
No es posible iniciar sesión, por favor intentelo mas tarde
</String>
<String id="Version">
Version
</String>
<String id="AppName">
Nombre de servicio
</String>
<String id="Close">
Cerrar
</String>
<String id="SideBar_Wording">
Lista de paneles:
</String>
<String id="SideBar_ColumnName_1">
Mostrar
</String>
<String id="SideBar_ColumnName_2">
Paneles
</String>
<String id="QuickStart_Wording">
Iconos de inicio rapido
</String>
<String id="QuickStart_ColumnName_1">
Mostrar
</String>
<String id="QuickStart_ColumnName_2">
Iconos
</String>
<String id="IDS_GROUP_0_LEVEL_TIPS">
Activar la corona
</String>
<String id="IDS_GROUP_LEVEL_TIPS">
Grupo de QQ de Corona de Grado $LVL$
</String>
<String id="QQ_Kickout_Text">
Estás fuera de línea porque se ha accedido a tu cuenta desde otro lugar.

Si no lo has hecho tú, es posible que alguien haya obtenido tu contraseña.
</String>
<String id="NewCustomHead_Tab_SystemHead">
Imagenes de perfil de sistema
</String>
<String id="NewCustomHead_Tab_VipHead">
会员头像
</String>
<String id="NewCustomHead_40_40">
40x40
</String>
<String id="Text_LatestWeek">
Semana pasada
</String>
<String id="Graffiti_Editor_Title">
editor de garabato
</String>
<String id="Graffiti_Editor_Confirm">
terminar
</String>
<String id="Graffiti_Editor_Cancel">
cancelar
</String>
<String id="Graffiti_Editor_Vip_Illustration_1">
Estimado cliente,
</String>
<String id="Graffiti_Editor_Vip_Illustration_2">
Aprovechar la herramienta avanzada de garabato y disfrutar la experiencia honorable.
</String>
<String id="Graffiti_Editor_Vip_Illustration_3">
Estimado socio de QQ, podría usar la herramienta de garabato gratis y disfrutar la experiencia honorable.
</String>
<String id="Graffiti_Editor_Open_Vip">
Activar socio de QQ
</String>
<String id="Graffiti_Editor_Learn_More">
Conocer los detalles funcionales
</String>
<String id="Graffiti_Editor_Add_To_Group">
Añadir a grupo:
</String>
<String id="Graffiti_Editor_Default_FontName">
Nuevo Song
</String>
<String id="Graffiti_Editor_DFC_FontName">
Microsoft Accor negro
</String>
<String id="Graffiti_Editor_Input_Prompt">
introducir palabras:
</String>
<String id="Graffiti_Editor_MakeDFC">
Finalizar
</String>
<String id="Graffiti_Editor_Limit_Text">
Alcanzado al número máximo del cuadro de texto.
</String>
<String id="Graffiti_Editor_Limit_Bubble">
彩色对话框数量已达上限。
</String>
<String id="Graffiti_Editor_Limit_DFC">
Alcanzado el número máximo de palabra de flash animada.
</String>
<String id="Graffiti_Editor_ToolTip_OpenFile">
Cargar imágenes locales
</String>
<String id="Graffiti_Editor_ToolTip_ZoomIn">
Ampliar imagen al fondo
</String>
<String id="Graffiti_Editor_ToolTip_ZoomOut">
Minorar imagen al fondo
</String>
<String id="Graffiti_Editor_ToolTip_Undo">
Revocar
</String>
<String id="Graffiti_Editor_ToolTip_Redo">
recuperar
</String>
<String id="Graffiti_Editor_ToolTip_Move">
Mover
</String>
<String id="Graffiti_Editor_ToolTip_Brush">
pincel
</String>
<String id="Graffiti_Editor_ToolTip_Text">
Cuadro de texto
</String>
<String id="Graffiti_Editor_ToolTip_Bubble">
Cuadro de diálogo en color
</String>
<String id="Graffiti_Editor_ToolTip_DFC">
Generar palabra de flash animada
</String>
<String id="Graffiti_Editor_Cancel_Prompt">
Está editando imagen de emociones, no se va a guardarla si sale ahora, ¿quiere salir todavía?
</String>
<String id="Graffiti_Editor_NoVip">
No es socio de QQ, registrarlo puede disfrutar la herramienta avanzada de garabato y otras 50 perrogativas de socio.
</String>
<String id="Graffiti_Editor_FormatError">
Lo sentimos, el formato de la imagen que ha cargado es incorrecto, vuelva a seleccionar la imagen.
</String>
<String id="Graffiti_Editor_SynthesisPrompt">
Generando imagen, espere un momento...
</String>
<String id="CF_SecurityTip_ConfigTime">
Configurar hora
</String>
<String id="CF_SecurityTip_ConfigTime_End">
-
</String>
<String id="Contacts_MainPanelTitle">
Agenda
</String>
<String id="IDS_SafeLogin">
安全登录
</String>
<String id="LoginPanel_Update">
Descargar ahora
</String>
<String id="LoginPanel_Close">
Cerrar
</String>
<String id="Finger_GroupNum">
ID del Grupo
</String>
<String id="Tips_QQClock">
Hora mundial
</String>
<String id="YouMayLikeTitle">
People You May Like
</String>
<String id="MsgMgr_NoFoundMsg">
Ningún resultado
</String>
<String id="MsgMgr_NoMsgs">
No hay mensajes
</String>
<String id="TmpChat_CommonFriends">
$FriendsNum$ amigos en común contigo. Agregar
</String>
<String id="TmpChat_CommonFriend">
$FriendsNum$ amigo en común contigo. Agregar
</String>
</StringBundle>
